text_embedder/__init__.py
text_embedder/embedder.py
text_embedder/utils.py
text_embedder-0.1.2.dist-info/LICENSE
text_embedder-0.1.2.dist-info/METADATA
text_embedder-0.1.2.dist-info/WHEEL
text_embedder-0.1.2.dist-info/top_level.txt
text_embedder-0.1.2.dist-info/RECORD
