Metadata-Version: 2.1
Name: text-embedder
Version: 0.1.2
Summary: A unified inference library for transformer-based pre-trained multilingual embedding models 
Author-email: Faheem <xdevfaheem@gmail.com>
License: MIT License
Project-URL: Repository, https://github.com/xdevfaheem/text_embedder
Project-URL: Issues, https://github.com/xdevfaheem/text_embedder/issues
Keywords: transformers,embeddings,NLP,rag,pytorch,huggingface,similarity
Classifier: Development Status :: 4 - Beta
Classifier: Intended Audience :: Developers
Classifier: Intended Audience :: Education
Classifier: License :: OSI Approved :: MIT License
Classifier: Programming Language :: Python :: 3
Classifier: Programming Language :: Python :: 3.7
Classifier: Programming Language :: Python :: 3.8
Classifier: Programming Language :: Python :: 3.9
Classifier: Programming Language :: Python :: 3.10
Classifier: Programming Language :: Python :: 3.12
Classifier: Topic :: Scientific/Engineering :: Artificial Intelligence
Requires-Python: >=3.7
License-File: LICENSE
